pymdt2json/__init__.py
pymdt2json/src/__init__.py
pymdt2json/src/cli.py
pymdt2json/src/parser.py
pymdt2json-0.5.0.dist-info/licenses/LICENSE
pymdt2json-0.5.0.dist-info/METADATA
pymdt2json-0.5.0.dist-info/WHEEL
pymdt2json-0.5.0.dist-info/entry_points.txt
pymdt2json-0.5.0.dist-info/top_level.txt
pymdt2json-0.5.0.dist-info/RECORD
