Metadata-Version: 2.4
Name: pymdt2json
Version: 0.5.0
Summary: Convert markdown tables into JSON code blocks
Home-page: https://github.com/amadou-6e/pymdt2json.git
Author: Amadou Wolfgang Cisse
Author-email: amadou.6e@googlemail.com
Classifier: Programming Language :: Python :: 3
Classifier: Operating System :: OS Independent
Requires-Python: >=3.7
License-File: LICENSE
Dynamic: author
Dynamic: author-email
Dynamic: classifier
Dynamic: home-page
Dynamic: license-file
Dynamic: requires-python
Dynamic: summary
